_config.py
_constants.py
_main.py
application/__init__.py
application/core/github_api.py
application/core/models/gemini_model.py
application/core/models/groq_model.py
application/utils/api.py
application/utils/helpers.py
application/utils/model_config.py
application/utils/parser.py
application/utils/validation.py
pyproject.toml
gh_echo-1.0.0.dist-info/LICENSE
gh_echo-1.0.0.dist-info/METADATA
gh_echo-1.0.0.dist-info/WHEEL
gh_echo-1.0.0.dist-info/entry_points.txt
gh_echo-1.0.0.dist-info/RECORD
