Metadata-Version: 2.1
Name: gh-echo
Version: 1.0.0
Summary: A command-line tool built to obtain in-depth, actionable information about GitHub repositories.
Home-page: https://pypi.org/project/gh-echo/o
License: MIT
Keywords: GitHub,GenAI,Python3,CLI
Author: Aryan Khurana
Author-email: aryankhurana1511@gmail.com
Requires-Python: >=3.9,<4.0
Classifier: License :: OSI Approved :: MIT License
Classifier: Operating System :: OS Independent
Classifier: Programming Language :: Python :: 3
Classifier: Programming Language :: Python :: 3.9
Classifier: Programming Language :: Python :: 3.10
Classifier: Programming Language :: Python :: 3.11
Classifier: Programming Language :: Python :: 3.12
Classifier: Programming Language :: Python :: 3.13
Requires-Dist: coverage (>=7.6.4,<8.0.0)
Requires-Dist: google-generativeai (>=0.8.0,<0.9.0)
Requires-Dist: groq (>=0.11.0,<0.12.0)
Requires-Dist: grpcio (>=1.68.0,<2.0.0)
Requires-Dist: httpx (>=0.27.2,<0.28.0)
Requires-Dist: pre-commit (>=4.0.1,<5.0.0)
Requires-Dist: pytest (>=8.3.3,<9.0.0)
Requires-Dist: pytest-watch (>=4.2.0,<5.0.0)
Requires-Dist: python-dotenv (>=1.0.1,<2.0.0)
Requires-Dist: ruff (>=0.6.4,<0.7.0)
Requires-Dist: single-source (>=0.4.0,<0.5.0)
Requires-Dist: toml (>=0.10.2,<0.11.0)
Requires-Dist: typer (>=0.12.5,<0.13.0)
Project-URL: Documentation, https://github.com/AryanK1511/github-echo/blob/main/README.md
Project-URL: Repository, https://github.com/AryanK1511/github-echo
